polidoro_command/__init__.py
polidoro_command/command.py
polidoro_command/polidoro_argument_parser.py
polidoro_command/polidoro_help_action.py
polidoro_command/polidoro_help_formatter.py
polidoro_command/polidoro_sub_parser_action.py
polidoro_command/utils.py
polidoro_command/tests/__init__.py
polidoro_command/tests/class_with_help.py
polidoro_command/tests/command_class.py
polidoro_command/tests/conftest.py
polidoro_command/tests/test_configs.py
polidoro_command/tests/test_help.py
polidoro_command/tests/test_run_failure.py
polidoro_command/tests/test_run_success.py
polidoro_command/tests/test_usage.py
polidoro_command-0.1.4.dist-info/LICENSE
polidoro_command-0.1.4.dist-info/METADATA
polidoro_command-0.1.4.dist-info/WHEEL
polidoro_command-0.1.4.dist-info/top_level.txt
polidoro_command-0.1.4.dist-info/RECORD
