Metadata-Version: 2.1
Name: polidoro-command
Version: 0.1.4
Summary: Package to create command line command in Python.
Home-page: https://github.com/heitorpolidoro/polidoro-command
Author: Heitor Polidoro
License: unlicense
Classifier: Programming Language :: Python :: 3.9
Classifier: License :: OSI Approved :: MIT License
Classifier: Operating System :: OS Independent
Requires-Python: >=3.9
License-File: LICENSE
